opentracing_async_instrumentation/__init__.py
opentracing_async_instrumentation/config.py
opentracing_async_instrumentation/http_client.py
opentracing_async_instrumentation/http_server.py
opentracing_async_instrumentation/utils.py
opentracing_async_instrumentation/client_hooks/__init__.py
opentracing_async_instrumentation/client_hooks/_dbapi2_async.py
opentracing_async_instrumentation/client_hooks/_patcher.py
opentracing_async_instrumentation/client_hooks/aioboto.py
opentracing_async_instrumentation/client_hooks/aiohttpclient.py
opentracing_async_instrumentation/client_hooks/aiohttpserver.py
opentracing_async_instrumentation/client_hooks/aiomysql.py
opentracing_async_instrumentation-0.2.1.dist-info/LICENSE
opentracing_async_instrumentation-0.2.1.dist-info/METADATA
opentracing_async_instrumentation-0.2.1.dist-info/WHEEL
opentracing_async_instrumentation-0.2.1.dist-info/top_level.txt
opentracing_async_instrumentation-0.2.1.dist-info/RECORD
