Metadata-Version: 2.1
Name: opentracing-async-instrumentation
Version: 0.2.1
Summary: Async Tracing Instrumentation using OpenTracing API (http://opentracing.io)
Home-page: https://gitlab.com/midigator/python_opentracing_async_instrumentation/
Author: Jessie Morris
Author-email: jessie.m@midigator.com
License: MIT
Keywords: opentracing,async,asyncio
Platform: any
Classifier: Development Status :: 5 - Production/Stable
Classifier: Intended Audience :: Developers
Classifier: License :: OSI Approved :: MIT License
Classifier: Programming Language :: Python :: 3.5
Classifier: Programming Language :: Python :: 3.6
Classifier: Programming Language :: Python :: 3.7
Classifier: Programming Language :: Python :: 3.8
Classifier: Programming Language :: Python :: Implementation :: PyPy
Classifier: Topic :: Software Development :: Libraries :: Python Modules
Requires-Python: >=3.5
Requires-Dist: future
Requires-Dist: wrapt
Requires-Dist: contextlib2
Requires-Dist: opentracing (<3,>=2)
Requires-Dist: six
Provides-Extra: tests
Requires-Dist: aiohttp ; extra == 'tests'
Requires-Dist: aiobotocore ; extra == 'tests'
Requires-Dist: aioboto3 ; extra == 'tests'
Requires-Dist: aiomysql ; extra == 'tests'
Requires-Dist: basictracer (<4,>=3) ; extra == 'tests'
Requires-Dist: flake8 ; extra == 'tests'
Requires-Dist: mock ; extra == 'tests'
Requires-Dist: moto[server] ; extra == 'tests'
Requires-Dist: pytest ; extra == 'tests'
Requires-Dist: pytest-cov ; extra == 'tests'
Requires-Dist: pytest-localserver ; extra == 'tests'
Requires-Dist: pytest-mock ; extra == 'tests'
Requires-Dist: pytest-asyncio ; extra == 'tests'
Requires-Dist: pytest-aiohttp ; extra == 'tests'
Requires-Dist: testfixtures ; extra == 'tests'
Requires-Dist: tox ; extra == 'tests'
